cdktf_cdktf_provider_opentelekomcloud/__init__.py
cdktf_cdktf_provider_opentelekomcloud/py.typed
cdktf_cdktf_provider_opentelekomcloud/_jsii/__init__.py
cdktf_cdktf_provider_opentelekomcloud/_jsii/provider-opentelekomcloud@12.0.13.jsii.tgz
cdktf_cdktf_provider_opentelekomcloud/antiddos_v1/__init__.py
cdktf_cdktf_provider_opentelekomcloud/apigw_acl_policy_associate_v2/__init__.py
cdktf_cdktf_provider_opentelekomcloud/apigw_acl_policy_v2/__init__.py
cdktf_cdktf_provider_opentelekomcloud/apigw_api_publishment_v2/__init__.py
cdktf_cdktf_provider_opentelekomcloud/apigw_api_v2/__init__.py
cdktf_cdktf_provider_opentelekomcloud/apigw_appcode_v2/__init__.py
cdktf_cdktf_provider_opentelekomcloud/apigw_application_authorization_v2/__init__.py
cdktf_cdktf_provider_opentelekomcloud/apigw_application_v2/__init__.py
cdktf_cdktf_provider_opentelekomcloud/apigw_certificate_v2/__init__.py
cdktf_cdktf_provider_opentelekomcloud/apigw_custom_authorizer_v2/__init__.py
cdktf_cdktf_provider_opentelekomcloud/apigw_environment_v2/__init__.py
cdktf_cdktf_provider_opentelekomcloud/apigw_environment_variable_v2/__init__.py
cdktf_cdktf_provider_opentelekomcloud/apigw_gateway_feature_v2/__init__.py
cdktf_cdktf_provider_opentelekomcloud/apigw_gateway_routes_v2/__init__.py
cdktf_cdktf_provider_opentelekomcloud/apigw_gateway_v2/__init__.py
cdktf_cdktf_provider_opentelekomcloud/apigw_group_v2/__init__.py
cdktf_cdktf_provider_opentelekomcloud/apigw_response_v2/__init__.py
cdktf_cdktf_provider_opentelekomcloud/apigw_signature_associate_v2/__init__.py
cdktf_cdktf_provider_opentelekomcloud/apigw_signature_v2/__init__.py
cdktf_cdktf_provider_opentelekomcloud/apigw_throttling_policy_associate_v2/__init__.py
cdktf_cdktf_provider_opentelekomcloud/apigw_throttling_policy_v2/__init__.py
cdktf_cdktf_provider_opentelekomcloud/apigw_vpc_channel_v2/__init__.py
cdktf_cdktf_provider_opentelekomcloud/as_configuration_v1/__init__.py
cdktf_cdktf_provider_opentelekomcloud/as_group_v1/__init__.py
cdktf_cdktf_provider_opentelekomcloud-12.0.13.dist-info/LICENSE
cdktf_cdktf_provider_opentelekomcloud-12.0.13.dist-info/METADATA
cdktf_cdktf_provider_opentelekomcloud-12.0.13.dist-info/WHEEL
cdktf_cdktf_provider_opentelekomcloud-12.0.13.dist-info/top_level.txt
cdktf_cdktf_provider_opentelekomcloud-12.0.13.dist-info/RECORD
